AUTHORS
LICENCE
MANIFEST.in
README.md
setup.py
django_thaidate.egg-info/PKG-INFO
django_thaidate.egg-info/SOURCES.txt
django_thaidate.egg-info/dependency_links.txt
django_thaidate.egg-info/not-zip-safe
django_thaidate.egg-info/top_level.txt
thaidate/__init__.py
thaidate/templatetags/thaidate.py