Metadata-Version: 1.1
Name: django-thaidate
Version: 1.0.2
Summary: Replacement for the "date" Django template tag to show Thai years
Home-page: https://github.com/joncombe/django-thaidate
Author: Jon Combe
Author-email: jon@naremit.com
License: BSD licence, see LICENCE file
Platform: UNKNOWN
Classifier: Development Status :: 3 - Alpha
Classifier: Environment :: Web Environment
Classifier: Framework :: Django
Classifier: Intended Audience :: Developers
Classifier: License :: OSI Approved :: BSD License
Classifier: Natural Language :: English
Classifier: Operating System :: OS Independent
Classifier: Programming Language :: Python
